odoo/addons/account_invoice_export_server_env/README.rst
odoo/addons/account_invoice_export_server_env/__init__.py
odoo/addons/account_invoice_export_server_env/__manifest__.py
odoo/addons/account_invoice_export_server_env/i18n/account_invoice_export_server_env.pot
odoo/addons/account_invoice_export_server_env/models/__init__.py
odoo/addons/account_invoice_export_server_env/models/transmit_method.py
odoo/addons/account_invoice_export_server_env/readme/DESCRIPTION.rst
odoo/addons/account_invoice_export_server_env/static/description/icon.png
odoo/addons/account_invoice_export_server_env/static/description/index.html
odoo13_addon_account_invoice_export_server_env-13.0.1.0.2.dist-info/METADATA
odoo13_addon_account_invoice_export_server_env-13.0.1.0.2.dist-info/WHEEL
odoo13_addon_account_invoice_export_server_env-13.0.1.0.2.dist-info/top_level.txt
odoo13_addon_account_invoice_export_server_env-13.0.1.0.2.dist-info/RECORD
