Metadata-Version: 2.1
Name: odoo13-addon-account-invoice-export-server-env
Version: 13.0.1.0.2
Summary: Server environment for Account Invoice Export
Home-page: https://github.com/OCA/edi
Author: Camptocamp,Odoo Community Association (OCA)
Author-email: support@odoo-community.org
License: AGPL-3
Platform: UNKNOWN
Classifier: Programming Language :: Python
Classifier: Framework :: Odoo
Classifier: Framework :: Odoo :: 13.0
Classifier: License :: OSI Approved :: GNU Affero General Public License v3
Requires-Python: >=3.5
Requires-Dist: odoo13-addon-account-invoice-export
Requires-Dist: odoo13-addon-server-environment
Requires-Dist: odoo (<13.1dev,>=13.0a)
